Workbook

Sheet README
A1: Caruthers Fair Band Showcase: planning workbook
A2: Purpose: test how the showcase's attendance, parking, budget and net result change when assumptions change.
A3: How to use: change any yellow cell on the Inputs sheet. Scenarios, Budget and Summary recalculate.
A4: Status: all attendance, parking and sponsor figures are planning assumptions. No published attendance or parking counts were found.
A5: Sheets: Inputs (assumptions and sources), Scenarios (low, base, high), Budget (line items), Summary (Monte Carlo), MC_Samples (2,000 simulated runs).
A6: Monte Carlo: 20,000 runs in Python (triangular inputs, seed 20270925). Summary percentiles use the 2,000-run sample in MC_Samples.

Sheet Inputs
A1: Input | B1: Low | C1: Base | D1: High | E1: Basis / source
A2: bands | B2: 10 | C2: 12 | D2: 16 | E2: Planning target for field-show bands (10 to 16)
A3: guests per band | B3: 80 | C3: 150 | D3: 250 | E3: Assumed family and guest count per band
A4: sat fair attendance | B4: 15000 | C4: 22000 | D4: 30000 | E4: Saturday share of 60k to 80k four-day estimate (2021 organizer estimate)
A5: walkup share | B5: 0.02 | C5: 0.05 | D5: 0.1 | E5: Share of Saturday fairgoers who watch the field show
A6: stand capacity | B6: 800 | C6: 1500 | D6: 2500 | E6: Bleacher capacity at the high school (unverified)
A7: occupancy | B7: 2.2 | C7: 2.8 | D7: 3.2 | E7: People per car (assumed)
A8: car share | B8: 0.7 | C8: 0.85 | D8: 0.95 | E8: Share of spectators arriving by car (assumed)
A9: fair lot share | B9: 0.3 | C9: 0.5 | D9: 0.8 | E9: Share of football-field parking used by the fair on Saturday (assumed)
A10: field spaces | B10: 250 | C10: 350 | D10: 450 | E10: Football-field parking spaces (unverified, to measure)
A11: elem spaces | B11: 80 | C11: 120 | D11: 160 | E11: Elementary lot spaces (unverified, to measure)
A12: hs spaces | B12: 80 | C12: 120 | D12: 160 | E12: High school lot spaces (unverified, to measure)
A13: trailer share | B13: 0.2 | C13: 0.4 | D13: 0.6 | E13: Share of bands bringing a trailer or bus to the lot
... A17: band fee | B17: 0 | C17: 100 | D17: 250 | E17: Participation fee per field-show band (policy choice)
A19: Contingency rate | C19: 0.15

Sheet Budget
A1: Budget line | B1: Low | C1: High | D1: Mid (base)
A2: Field and facility use | B2: 500 | C2: 1500 | D2: =AVERAGE(B2:C2)
A3: Liability insurance | B3: 500 | C3: 1500 | D3: =AVERAGE(B3:C3)
A4: Traffic and crossing control | B4: 1000 | C4: 2500 | D4: =AVERAGE(B4:C4)
A5: Portable restrooms | B5: 600 | C5: 1200 | D5: =AVERAGE(B5:C5)
A6: Sound and staging | B6: 600 | C6: 1500 | D6: =AVERAGE(B6:C6)
A7: Judges (3 to 4) | B7: 600 | C7: 1600 | D7: =AVERAGE(B7:C7)
A8: Clinicians (2) | B8: 800 | C8: 1600 | D8: =AVERAGE(B8:C8)
A9: Plaques, programs, signage | B9: 500 | C9: 1200 | D9: =AVERAGE(B9:C9)
A10: Fire and EMS standby (added) | B10: 0 | C10: 1000 | D10: =AVERAGE(B10:C10)
A11: Trailer staging, fencing and signage (added) | B11: 300 | C11: 1200 | D11: =AVERAGE(B11:C11)
A12: Subtotal | B12: =SUM(B2:B11) | C12: =SUM(C2:C11) | D12: =SUM(D2:D11)
A13: Contingency | B13: =B12*Inputs!$C$19 | C13: =C12*Inputs!$C$19 | D13: =D12*Inputs!$C$19
A14: Total | B14: =B12+B13 | C14: =C12+C13 | D14: =D12+D13

Sheet Scenarios
A1: Output | B1: Low case (low inputs) | C1: Base case | D1: High case (high inputs) | E1: Formula note
A2: Bands (field show) | B2: =ROUND(Inputs!$B$2,0) | C2: =ROUND(Inputs!$C$2,0) | D2: =ROUND(Inputs!$D$2,0)
A3: Band guests | B3: =B2*Inputs!$B$3 | C3: =C2*Inputs!$C$3 | D3: =D2*Inputs!$D$3
A4: Walk-up spectators | B4: =Inputs!$B$5*Inputs!$B$4 | C4: =Inputs!$C$5*Inputs!$C$4 | D4: =Inputs!$D$5*Inputs!$D$4
A5: Seated spectators (capped) | B5: =MIN(B3+B4,Inputs!$B$6) | C5: =MIN(C3+C4,Inputs!$C$6) | D5: =MIN(D3+D4,Inputs!$D$6)
A6: Cars arriving | B6: =B5*Inputs!$B$8/Inputs!$B$7 | C6: =C5*Inputs!$C$8/Inputs!$C$7 | D6: =D5*Inputs!$D$8/Inputs!$D$7
A7: Vehicles needing space | B7: =B6+B2*Inputs!$B$14 | C7: =C6+C2*Inputs!$C$14 | D7: =D6+D2*Inputs!$D$14
A8: Usable parking spaces | B8: =Inputs!$B$10*(1-Inputs!$B$9)+Inputs!$B$11+Inputs!$B$12 | C8: =Inputs!$C$10*(1-Inputs!$C$9)+Inputs!$C$11+Inputs!$C$12 | D8: =Inputs!$D$10*(1-Inputs!$D$9)+Inputs!$D$11+Inputs!$D$12
A9: Parking shortfall (vehicles) | B9: =MAX(B7-B8,0) | C9: =MAX(C7-C8,0) | D9: =MAX(D7-D8,0)
A10: Revenue | B10: =B5*Inputs!$B$15+Inputs!$B$16+B2*Inputs!$B$17 | C10: =C5*Inputs!$C$15+Inputs!$C$16+C2*Inputs!$C$17 | D10: =D5*Inputs!$D$15+Inputs!$D$16+D2*Inputs!$D$17
A11: Cost (budget with contingency) | B11: =Budget!$D$14 | C11: =Budget!$D$14 | D11: =Budget!$D$14
A12: Net result | B12: =B10-B11 | C12: =C10-C11 | D12: =D10-D11 | E12: Cost uses the budget midpoint; the Monte Carlo draws each line separately.

Sheet Summary
A1: Measure | B1: P10 | C1: P50 | D1: P90 | E1: Note
A2: Seated spectators | B2: =PERCENTILE(MC_Samples!$B$2:$B$2001,0.1) | C2: =PERCENTILE(MC_Samples!$B$2:$B$2001,0.5) | D2: =PERCENTILE(MC_Samples!$B$2:$B$2001,0.9) | E2: Capped at stand capacity
A3: Cars arriving | B3: =PERCENTILE(MC_Samples!$C$2:$C$2001,0.1) | C3: =PERCENTILE(MC_Samples!$C$2:$C$2001,0.5) | D3: =PERCENTILE(MC_Samples!$C$2:$C$2001,0.9)
A4: Vehicles needing space | B4: =PERCENTILE(MC_Samples!$D$2:$D$2001,0.1) | C4: =PERCENTILE(MC_Samples!$D$2:$D$2001,0.5) | D4: =PERCENTILE(MC_Samples!$D$2:$D$2001,0.9) | E4: Cars plus band vehicles
A5: Usable parking spaces | B5: =PERCENTILE(MC_Samples!$E$2:$E$2001,0.1) | C5: =PERCENTILE(MC_Samples!$E$2:$E$2001,0.5) | D5: =PERCENTILE(MC_Samples!$E$2:$E$2001,0.9) | E5: Football field net of fair share, plus two school lots
A6: Cost | B6: =PERCENTILE(MC_Samples!$F$2:$F$2001,0.1) | C6: =PERCENTILE(MC_Samples!$F$2:$F$2001,0.5) | D6: =PERCENTILE(MC_Samples!$F$2:$F$2001,0.9) | E6: With contingency
A7: Revenue | B7: =PERCENTILE(MC_Samples!$G$2:$G$2001,0.1) | C7: =PERCENTILE(MC_Samples!$G$2:$G$2001,0.5) | D7: =PERCENTILE(MC_Samples!$G$2:$G$2001,0.9) | E7: Donations, sponsor, band fees
A8: Net result | B8: =PERCENTILE(MC_Samples!$H$2:$H$2001,0.1) | C8: =PERCENTILE(MC_Samples!$H$2:$H$2001,0.5) | D8: =PERCENTILE(MC_Samples!$H$2:$H$2001,0.9) | E8: Negative means the event needs outside funding
A10: Share of runs with a parking shortfall | B10: 0.80365
A11: Share of runs at break-even or better | B11: =COUNTIF(MC_Samples!$H$2:$H$2001,">=0")/2000
A13: The shortfall share and the break-even share come from the full 20,000-run simulation; the sample column shows the same measure from 2,000 runs.

Sheet MC_Samples
A1: run | B1: spectators | C1: cars | D1: lot_demand | E1: supply | F1: cost | G1: revenue | H1: net
A2: 1 | B2: 1416.11 | C2: 520.32 | D2: 546.32 | E2: 427.84 | F2: 11333.72 | G2: 3521.78 | H2: -7811.94
A3: 2 | B3: 1114.68 | C3: 330.71 | D3: 354.71 | E3: 388.02 | F3: 11438.13 | G3: 6303.91 | H3: -5134.22
A4: 3 | B4: 1134.9 | C4: 340.11 | D4: 356.11 | E4: 385.12 | F4: 12125.31 | G4: 3166.77 | H4: -8958.54
A5: 4 | B5: 2085.76 | C5: 697.24 | D5: 723.24 | E5: 383.1 | F5: 11755.75 | G5: 2875.39 | H5: -8880.36
A6: 5 | B6: 1639.66 | C6: 528.68 | D6: 573.68 | E6: 395.54 | F6: 12186.72 | G6: 5164.73 | H6: -7021.99
A7: 6 | B7: 1052.33 | C7: 324.15 | D7: 348.15 | E7: 446.68 | F7: 11500.43 | G7: 2950.79 | H7: -8549.64
A8: 7 | B8: 2064.3 | C8: 628.99 | D8: 650.99 | E8: 457.03 | F8: 12727.55 | G8: 3320.64 | H8: -9406.91
A9: 8 | B9: 1794.18 | C9: 522.41 | D9: 550.41 | E9: 324.7 | F9: 10757.46 | G9: 4713.17 | H9: -6044.29
A10: 9 | B10: 1320.05 | C10: 457.81 | D10: 487.81 | E10: 395.38 | F10: 10204.83 | G10: 4109.95 | H10: -6094.88
A11: 10 | B11: 1456.61 | C11: 484.87 | D11: 510.87 | E11: 438.17 | F11: 12586.25 | G11: 5017.07 | H11: -7569.18
A12: 11 | B12: 1548.75 | C12: 489.66 | D12: 509.66 | E12: 446.99 | F12: 10547.47 | G12: 3685.68 | H12: -6861.78
A13: 12 | B13: 1098.44 | C13: 287.79 | D13: 299.79 | E13: 445.68 | F13: 11815.99 | G13: 2714.64 | H13: -9101.35
... A2001: 2000 | B2001: 1480.71 | C2001: 403.35 | D2001: 427.35 | E2001: 402.64 | F2001: 13063.54 | G2001: 6857.91 | H2001: -6205.63
